odd_kernel/__init__.py
odd_kernel/datasets/__init__.py
odd_kernel/datasets/cryptocurrencies.py
odd_kernel/datasets/marketdata.py
odd_kernel/util/__init__.py
odd_kernel/util/charts.py
odd_kernel/util/general.py
odd_kernel/util/mailing.py
odd_kernel/util/misc.py
odd_kernel/util/timing.py
odd_kernel/util/assets/ding.wav
odd_kernel/util/interpolation/__init__.py
odd_kernel/util/interpolation/gaussian_kde.py
odd_kernel/util/interpolation/knn.py
odd_kernel/util/interpolation/util.py
tests/__init__.py
tests/test_cryptocurrencies.py
tests/test_marketdata.py
tests/test_util_misc.py
odd_kernel-0.1.30.dist-info/METADATA
odd_kernel-0.1.30.dist-info/WHEEL
odd_kernel-0.1.30.dist-info/top_level.txt
odd_kernel-0.1.30.dist-info/RECORD
