Metadata-Version: 2.4
Name: odd_kernel
Version: 0.1.30
Summary: Some wrappers for python utilities.
Home-page: https://github.com/pereradrian/odd-kernel
Author: OddKernel
Author-email: odd.kernel.sl@gmail.com
Classifier: Programming Language :: Python :: 3
Classifier: License :: OSI Approved :: MIT License
Classifier: Operating System :: OS Independent
Requires-Python: >=3.11
Requires-Dist: yfinance
Requires-Dist: pandas
Requires-Dist: numpy
Dynamic: author
Dynamic: author-email
Dynamic: classifier
Dynamic: home-page
Dynamic: requires-dist
Dynamic: requires-python
Dynamic: summary
